{
  "tiers": [
    {
      "name": "Bronze",
      "summary": "Information Services",
      "price": 100,
      "growth_stage": "sapling",
      "services": [
        {
          "title": "Access Information",
          "subservices": [
            "Access verified information about waste reduction.",
            "Access verified information about circular economy.",
            "Access verified information about resource recovery issues.",
            "Access CIC research and publications.",
            "Access the Resource Library.",
            "Receive notifications for workshops, forums, and events."
          ],
          "preferred_year": "year1"
        },
        {
          "title": "Stay Informed",
          "subservices": [
            "Email list about circular news and events from around the world.",
            "Email list about policy and industry updates.",
            "Email list about partner events.",
            "Circular Innovation Council announcements and updates."
          ],
          "preferred_year": "year1"
        },
        {
          "title": "Multi-Sectoral Perspectives",
          "subservices": [
            "Neutral-setting discussions about priority environmental issues.",
            "Perspectives from governments, industry, SMEs, individuals, non-profits, and more."
          ],
          "preferred_year": "year1"
        }
      ]
    },
    {
      "name": "Silver",
      "summary": "Relationship Services + Financial Services",
      "price": 100,
      "growth_stage": "branching",
      "services": [
        {
          "title": "Networking Forum",
          "subservices": [
            "Connect with governments of all levels.",
            "Connect with environmental non-profits.",
            "Connect with environmental consultants and businesses."
          ],
          "preferred_year": "year2"
        },
        {
          "title": "Reduced Rates",
          "subservices": [
            "Reduced rates for forums.",
            "Reduced rates for workshops.",
            "Reduced rates for seminars.",
            "Reduced rates for CIC or partner special events."
          ],
          "preferred_year": "year2"
        }
      ]
    },
    {
      "name": "Gold",
      "summary": "Influential Services",
      "price": 100,
      "growth_stage": "full_tree",
      "services": [
        {
          "title": "Voting Privileges",
          "subservices": [
            "Vote at the annual general meeting.",
            "Run for a seat on the Board of Directors.",
            "Participate in the Program Development Committee.",
            "Participate in the Event Committee."
          ],
          "preferred_year": "year3"
        },
        {
          "title": "Influence",
          "subservices": [
            "Influence policy inputs.",
            "Influence how CIC adapts its policies to changing conditions and government perspectives."
          ],
          "preferred_year": "year3"
        }
      ]
    }
  ]
}
